portune/__init__.py
portune/portune.py
portune/version.py
portune-1.0.14.dist-info/licenses/LICENSE
portune-1.0.14.dist-info/METADATA
portune-1.0.14.dist-info/WHEEL
portune-1.0.14.dist-info/entry_points.txt
portune-1.0.14.dist-info/top_level.txt
portune-1.0.14.dist-info/RECORD
