Metadata-Version: 2.4
Name: portune
Version: 1.0.14
Summary: Simple Python HTTP Exec Server
Author: Franck Jouvanceau
Maintainer: Franck Jouvanceau
License-Expression: MIT
Project-URL: Homepage, https://github.com/joknarf/portune
Project-URL: Documentation, https://github.com/joknarf/portune/blob/main/README.md
Project-URL: Repository, https://github.com/joknarf/portune.git
Keywords: port,scanner,html_report
Classifier: Development Status :: 5 - Production/Stable
Classifier: Intended Audience :: System Administrators
Classifier: Operating System :: POSIX
Classifier: Operating System :: Unix
Classifier: Operating System :: MacOS
Classifier: Operating System :: Microsoft :: Windows
Classifier: Programming Language :: Python
Classifier: Programming Language :: Python :: 3
Classifier: Programming Language :: Python :: 3.9
Classifier: Programming Language :: Python :: 3.10
Classifier: Programming Language :: Python :: 3.11
Classifier: Programming Language :: Python :: 3.12
Classifier: Programming Language :: Python :: 3.13
Classifier: Topic :: Software Development :: Libraries :: Python Modules
Classifier: Topic :: System :: Clustering
Classifier: Topic :: System :: Networking
Classifier: Topic :: System :: Systems Administration
Requires-Python: >=3.9
License-File: LICENSE
Dynamic: license-file
